
{"items":[{"name":"RiotApiStats.Models.DTOs","href":"RiotApiStats.Models.DTOs.html","topicHref":"RiotApiStats.Models.DTOs.html","topicUid":"RiotApiStats.Models.DTOs","type":"Namespace","items":[{"name":"ParticipantDTO","href":"RiotApiStats.Models.DTOs.ParticipantDTO.html","topicHref":"RiotApiStats.Models.DTOs.ParticipantDTO.html","topicUid":"RiotApiStats.Models.DTOs.ParticipantDTO","type":"Class"}]},{"name":"RiotApiStats.Pages","href":"RiotApiStats.Pages.html","topicHref":"RiotApiStats.Pages.html","topicUid":"RiotApiStats.Pages","type":"Namespace","items":[{"name":"ErrorModel","href":"RiotApiStats.Pages.ErrorModel.html","topicHref":"RiotApiStats.Pages.ErrorModel.html","topicUid":"RiotApiStats.Pages.ErrorModel","type":"Class"},{"name":"IndexModel","href":"RiotApiStats.Pages.IndexModel.html","topicHref":"RiotApiStats.Pages.IndexModel.html","topicUid":"RiotApiStats.Pages.IndexModel","type":"Class"},{"name":"PrivacyModel","href":"RiotApiStats.Pages.PrivacyModel.html","topicHref":"RiotApiStats.Pages.PrivacyModel.html","topicUid":"RiotApiStats.Pages.PrivacyModel","type":"Class"}]},{"name":"RiotStatsAPI.Controllers","href":"RiotStatsAPI.Controllers.html","topicHref":"RiotStatsAPI.Controllers.html","topicUid":"RiotStatsAPI.Controllers","type":"Namespace","items":[{"name":"HelloController","href":"RiotStatsAPI.Controllers.HelloController.html","topicHref":"RiotStatsAPI.Controllers.HelloController.html","topicUid":"RiotStatsAPI.Controllers.HelloController","type":"Class"},{"name":"RiotController","href":"RiotStatsAPI.Controllers.RiotController.html","topicHref":"RiotStatsAPI.Controllers.RiotController.html","topicUid":"RiotStatsAPI.Controllers.RiotController","type":"Class"}]},{"name":"RiotStatsAPI.Data","href":"RiotStatsAPI.Data.html","topicHref":"RiotStatsAPI.Data.html","topicUid":"RiotStatsAPI.Data","type":"Namespace","items":[{"name":"AppDbContext","href":"RiotStatsAPI.Data.AppDbContext.html","topicHref":"RiotStatsAPI.Data.AppDbContext.html","topicUid":"RiotStatsAPI.Data.AppDbContext","type":"Class"}]},{"name":"RiotStatsAPI.Migrations","href":"RiotStatsAPI.Migrations.html","topicHref":"RiotStatsAPI.Migrations.html","topicUid":"RiotStatsAPI.Migrations","type":"Namespace","items":[{"name":"AddSummonerEntity","href":"RiotStatsAPI.Migrations.AddSummonerEntity.html","topicHref":"RiotStatsAPI.Migrations.AddSummonerEntity.html","topicUid":"RiotStatsAPI.Migrations.AddSummonerEntity","type":"Class"},{"name":"FixedRelationships","href":"RiotStatsAPI.Migrations.FixedRelationships.html","topicHref":"RiotStatsAPI.Migrations.FixedRelationships.html","topicUid":"RiotStatsAPI.Migrations.FixedRelationships","type":"Class"},{"name":"InitialCreate","href":"RiotStatsAPI.Migrations.InitialCreate.html","topicHref":"RiotStatsAPI.Migrations.InitialCreate.html","topicUid":"RiotStatsAPI.Migrations.InitialCreate","type":"Class"},{"name":"InitialMigration","href":"RiotStatsAPI.Migrations.InitialMigration.html","topicHref":"RiotStatsAPI.Migrations.InitialMigration.html","topicUid":"RiotStatsAPI.Migrations.InitialMigration","type":"Class"},{"name":"MigrationAccount_sync","href":"RiotStatsAPI.Migrations.MigrationAccount_sync.html","topicHref":"RiotStatsAPI.Migrations.MigrationAccount_sync.html","topicUid":"RiotStatsAPI.Migrations.MigrationAccount_sync","type":"Class"},{"name":"MigrationChampionLevel","href":"RiotStatsAPI.Migrations.MigrationChampionLevel.html","topicHref":"RiotStatsAPI.Migrations.MigrationChampionLevel.html","topicUid":"RiotStatsAPI.Migrations.MigrationChampionLevel","type":"Class"},{"name":"MigrationChampionName","href":"RiotStatsAPI.Migrations.MigrationChampionName.html","topicHref":"RiotStatsAPI.Migrations.MigrationChampionName.html","topicUid":"RiotStatsAPI.Migrations.MigrationChampionName","type":"Class"},{"name":"MigrationItems_Teamid","href":"RiotStatsAPI.Migrations.MigrationItems_Teamid.html","topicHref":"RiotStatsAPI.Migrations.MigrationItems_Teamid.html","topicUid":"RiotStatsAPI.Migrations.MigrationItems_Teamid","type":"Class"},{"name":"MigrationParticipant","href":"RiotStatsAPI.Migrations.MigrationParticipant.html","topicHref":"RiotStatsAPI.Migrations.MigrationParticipant.html","topicUid":"RiotStatsAPI.Migrations.MigrationParticipant","type":"Class"},{"name":"MigrationParticipant_EDIT","href":"RiotStatsAPI.Migrations.MigrationParticipant_EDIT.html","topicHref":"RiotStatsAPI.Migrations.MigrationParticipant_EDIT.html","topicUid":"RiotStatsAPI.Migrations.MigrationParticipant_EDIT","type":"Class"},{"name":"MigrationParticipant_type_change","href":"RiotStatsAPI.Migrations.MigrationParticipant_type_change.html","topicHref":"RiotStatsAPI.Migrations.MigrationParticipant_type_change.html","topicUid":"RiotStatsAPI.Migrations.MigrationParticipant_type_change","type":"Class"},{"name":"UpdateSummonerEntity","href":"RiotStatsAPI.Migrations.UpdateSummonerEntity.html","topicHref":"RiotStatsAPI.Migrations.UpdateSummonerEntity.html","topicUid":"RiotStatsAPI.Migrations.UpdateSummonerEntity","type":"Class"}]},{"name":"RiotStatsAPI.Models.DTOs","href":"RiotStatsAPI.Models.DTOs.html","topicHref":"RiotStatsAPI.Models.DTOs.html","topicUid":"RiotStatsAPI.Models.DTOs","type":"Namespace","items":[{"name":"AccountDTO","href":"RiotStatsAPI.Models.DTOs.AccountDTO.html","topicHref":"RiotStatsAPI.Models.DTOs.AccountDTO.html","topicUid":"RiotStatsAPI.Models.DTOs.AccountDTO","type":"Class"},{"name":"InfoDTO","href":"RiotStatsAPI.Models.DTOs.InfoDTO.html","topicHref":"RiotStatsAPI.Models.DTOs.InfoDTO.html","topicUid":"RiotStatsAPI.Models.DTOs.InfoDTO","type":"Class"},{"name":"MatchDTO","href":"RiotStatsAPI.Models.DTOs.MatchDTO.html","topicHref":"RiotStatsAPI.Models.DTOs.MatchDTO.html","topicUid":"RiotStatsAPI.Models.DTOs.MatchDTO","type":"Class"},{"name":"MetaDataDTO","href":"RiotStatsAPI.Models.DTOs.MetaDataDTO.html","topicHref":"RiotStatsAPI.Models.DTOs.MetaDataDTO.html","topicUid":"RiotStatsAPI.Models.DTOs.MetaDataDTO","type":"Class"},{"name":"SummonerDto","href":"RiotStatsAPI.Models.DTOs.SummonerDto.html","topicHref":"RiotStatsAPI.Models.DTOs.SummonerDto.html","topicUid":"RiotStatsAPI.Models.DTOs.SummonerDto","type":"Class"}]},{"name":"RiotStatsAPI.Models.Entities","href":"RiotStatsAPI.Models.Entities.html","topicHref":"RiotStatsAPI.Models.Entities.html","topicUid":"RiotStatsAPI.Models.Entities","type":"Namespace","items":[{"name":"Account","href":"RiotStatsAPI.Models.Entities.Account.html","topicHref":"RiotStatsAPI.Models.Entities.Account.html","topicUid":"RiotStatsAPI.Models.Entities.Account","type":"Class"},{"name":"Matches","href":"RiotStatsAPI.Models.Entities.Matches.html","topicHref":"RiotStatsAPI.Models.Entities.Matches.html","topicUid":"RiotStatsAPI.Models.Entities.Matches","type":"Class"},{"name":"Participant","href":"RiotStatsAPI.Models.Entities.Participant.html","topicHref":"RiotStatsAPI.Models.Entities.Participant.html","topicUid":"RiotStatsAPI.Models.Entities.Participant","type":"Class"},{"name":"Summoner","href":"RiotStatsAPI.Models.Entities.Summoner.html","topicHref":"RiotStatsAPI.Models.Entities.Summoner.html","topicUid":"RiotStatsAPI.Models.Entities.Summoner","type":"Class"}]},{"name":"RiotStatsAPI.Services","href":"RiotStatsAPI.Services.html","topicHref":"RiotStatsAPI.Services.html","topicUid":"RiotStatsAPI.Services","type":"Namespace","items":[{"name":"RiotApiService","href":"RiotStatsAPI.Services.RiotApiService.html","topicHref":"RiotStatsAPI.Services.RiotApiService.html","topicUid":"RiotStatsAPI.Services.RiotApiService","type":"Class"}]}],"memberLayout":"SamePage","pdf":true}
